<?xml version="1.0" encoding="UTF-8"?>
<monster name="Kimimaro" nameDescription="Kimimaro" race="blood" experience="6200" speed="650" manacost="0">
	<health now="78245" max="78245"/>
	<look type="194" head="0" body="94" legs="79" feet="79" corpse="19259"/>
	<targetchange interval="5000" chance="8"/>
	<strategy attack="90" defense="20"/>
	<flags>
		<flag summonable="1"/>
		<flag attackable="1"/>
		<flag hostile="1"/>
		<flag illusionable="0"/>
		<flag convinceable="1"/>
		<flag pushable="0"/>
		<flag canpushitems="1"/>
		<flag canpushcreatures="1"/>
		<flag targetdistance="1"/>
		<flag staticattack="65"/>
		<flag passive="0" /> 
		<flag runonhealth="0"/>
	</flags>  
	<attacks>
		<attack name="melee" interval="1500" min="-9180" max="-10100"/>
		<attack name="ossokimimaro" interval="2000" chance="100" radius="4" target="0" min="-8480" max="-9500">
		</attack>
	</attacks>
	<loot>
		<item id="16473" countmax="2" chance="7000"/><!-- pilula do soldado -->
	</loot>
</monster>